basebender/STRUCTURE.md
basebender/__init__.py
basebender/api/STRUCTURE.md
basebender/api/main.py
basebender/cli.py
basebender/gui/STRUCTURE.md
basebender/gui/__init__.py
basebender/gui/main_window.py
basebender/rebaser/STRUCTURE.md
basebender/rebaser/__init__.py
basebender/rebaser/config_loader.py
basebender/rebaser/digit_set_rebaser.py
basebender/rebaser/digit_sets.py
basebender/rebaser/generated/STRUCTURE.md
basebender/rebaser/generated/__init__.py
basebender/rebaser/generated/app_resources_rc.py
basebender/rebaser/models.py
basebender/rebaser/resources/STRUCTURE.md
basebender/rebaser/resources/app_resources.qrc
basebender/rebaser/resources/data/STRUCTURE.md
basebender/rebaser/resources/data/default_digit_sets.toml
basebender/rebaser/resources/icons/STRUCTURE.md
basebender/rebaser/resources/icons/input.svg
basebender/rebaser/resources/icons/output.svg
basebender/rebaser/resources/icons/source.svg
basebender/rebaser/resources/icons/target.svg
basebender-0.1.6.dist-info/METADATA
basebender-0.1.6.dist-info/WHEEL
basebender-0.1.6.dist-info/entry_points.txt
basebender-0.1.6.dist-info/licenses/LICENSE
basebender-0.1.6.dist-info/RECORD
