Metadata-Version: 2.4
Name: basebender
Version: 0.1.6
Summary: A Python module for rebaseing strings between different digit sets (positional number systems).
License: MIT License
License-File: LICENSE
Author: by.a.mexc@gmail.com
Requires-Python: >=3.13,<3.14
Classifier: License :: Other/Proprietary License
Classifier: Programming Language :: Python :: 3
Classifier: Programming Language :: Python :: 3.13
Requires-Dist: fastapi (>=0.115.12,<1.0.0)
Requires-Dist: platformdirs (>=4.2.0,<5.0.0)
Requires-Dist: poetry-core (>=2.0.0)
Requires-Dist: pyside6 (>=6.9.0,<7.0.0)
Requires-Dist: toml (>=0.10.2,<0.11.0)
Requires-Dist: uvicorn (>=0.34.3,<1.0.0)
Project-URL: Homepage, https://github.com/meXc/BaseBender
Project-URL: Issues, https://github.com/meXc/BaseBender/issues
Project-URL: Repository, https://github.com/meXc/BaseBender.git
